LICENSE.md
MANIFEST.in
README
README.md
setup.py
submarine_githooks/__init__.py
submarine_githooks/checker.py
submarine_githooks/constants.py
submarine_githooks/content.py
submarine_githooks/hooks.py
submarine_githooks/main.py
submarine_githooks.egg-info/PKG-INFO
submarine_githooks.egg-info/SOURCES.txt
submarine_githooks.egg-info/dependency_links.txt
submarine_githooks.egg-info/entry_points.txt
submarine_githooks.egg-info/pbr.json
submarine_githooks.egg-info/requires.txt
submarine_githooks.egg-info/top_level.txt
submarine_githooks/contrib/__init__.py
submarine_githooks/contrib/checkers/__init__.py
submarine_githooks/contrib/checkers/json_content.py